README.md
setup.py
hilbert/__init__.py
hilbert/decode.py
hilbert/encode.py
hilbert/gray.py
numpy_hilbert_curve.egg-info/PKG-INFO
numpy_hilbert_curve.egg-info/SOURCES.txt
numpy_hilbert_curve.egg-info/dependency_links.txt
numpy_hilbert_curve.egg-info/top_level.txt