Metadata-Version: 2.1
Name: numpy-hilbert-curve
Version: 1.0.1
Summary: Implements Hilbert space-filling curves for Python with numpy
Home-page: https://github.com/PrincetonLIPS/numpy-hilbert-curve
Author: Ryan P. Adams
Author-email: rpa@princeton.edu
License: MIT
Platform: UNKNOWN
Classifier: Development Status :: 4 - Beta
Classifier: Intended Audience :: Science/Research
Classifier: License :: OSI Approved :: MIT License
